<?xml version="1.0"?>
<hospital>
    <patient>
        <name>
            <firstName>Abi</firstName>
            <middleName>Shek</middleName>
            <lastName>Neupane</lastName>
        </name>
        <ssn>1499</ssn>
        <age>21</age>
        <roomNumber>11</roomNumber>
        <primaryInsuranceCompany>
            <memberIdentificationNumber>2079/21</memberIdentificationNumber>
            <groupNumber>A1</groupNumber>
            <address>Bharatpur</address>
        </primaryInsuranceCompany>
    </patient>
</hospital>
